PyLibreHardwareMonitorLib/__init__.py
PyLibreHardwareMonitorLib/dll/HidSharp.dll
PyLibreHardwareMonitorLib/dll/LICENSE
PyLibreHardwareMonitorLib/dll/v0.8.5/LibreHardwareMonitorLib.dll
PyLibreHardwareMonitorLib/dll/v0.8.6/LibreHardwareMonitorLib.dll
PyLibreHardwareMonitorLib/dll/v0.8.7/LibreHardwareMonitorLib.dll
PyLibreHardwareMonitorLib/dll/v0.8.8/LibreHardwareMonitorLib.dll
PyLibreHardwareMonitorLib/dll/v0.8.9/LibreHardwareMonitorLib.dll
PyLibreHardwareMonitorLib/dll/v0.9.0/LibreHardwareMonitorLib.dll
PyLibreHardwareMonitorLib/dll/v0.9.1/LibreHardwareMonitorLib.dll
PyLibreHardwareMonitorLib/dll/v0.9.2/LibreHardwareMonitorLib.dll
PyLibreHardwareMonitorLib/dll/v0.9.3/LibreHardwareMonitorLib.dll
PyLibreHardwareMonitorLib/dll/v0.9.4/LibreHardwareMonitorLib.dll
PyLibreHardwareMonitorLib-1.2.1.dist-info/LICENSE
PyLibreHardwareMonitorLib-1.2.1.dist-info/METADATA
PyLibreHardwareMonitorLib-1.2.1.dist-info/WHEEL
PyLibreHardwareMonitorLib-1.2.1.dist-info/top_level.txt
PyLibreHardwareMonitorLib-1.2.1.dist-info/RECORD
