Metadata-Version: 2.1
Name: PyLibreHardwareMonitorLib
Version: 1.2.1
Summary: A Python library for LibreHardwareMonitor DLL integration
Author-email: jianjun <910667956@qq.com>
License: Mozilla Public License Version 2.0
Project-URL: homepage, https://github.com/EVA-JianJun/PyLibreHardwareMonitorLib
Project-URL: repository, https://github.com/EVA-JianJun/PyLibreHardwareMonitorLib
Requires-Python: >=3.6
License-File: LICENSE
Requires-Dist: pythonnet
